{"phases": ["Liquid"], "ref": {"full": "Krishna, T. S.; Raju, K. T. S. S.; Gowrisankar, M.; Nain, A. K.; Munibhadrayya, B. (2016) J. Mol. Liq. 216, 484-495.", "title": "Volumetric, ultrasonic and spectroscopic studies of molecular interactions in binary mixtures of 1-butyl-3-methylimidazolium hexafluorophosphate with 2-propoxyethanol at temperatures from 298.15 to 323.15 K"}, "constr": [], "expmeth": "Standard Abbe refractometry", "data": [[["298.15"], ["0"], ["101"], ["1.41034", "0.00061"]], [["298.15"], ["0.1127"], ["101"], ["1.41248", "0.00053"]], [["298.15"], ["0.1957"], ["101"], ["1.41334", "0.00052"]], [["298.15"], ["0.298"], ["101"], ["1.41358", "0.00052"]], [["298.15"], ["0.3832"], ["101"], ["1.41335", "0.00052"]], [["298.15"], ["0.4881"], ["101"], ["1.41278", "0.00052"]], [["298.15"], ["0.6047"], ["101"], ["1.41195", "0.00051"]], [["298.15"], ["0.6937"], ["101"], ["1.4113", "0.00051"]], [["298.15"], ["0.8055"], ["101"], ["1.41048", "0.00051"]], [["298.15"], ["0.8532"], ["101"], ["1.4101", "0.00051"]], [["298.15"], ["1"], ["101"], ["1.40902", "0.00052"]], [["303.15"], ["0"], ["101"], ["1.4081", "0.00061"]], [["303.15"], ["0.1127"], ["101"], ["1.4105", "0.00057"]], [["303.15"], ["0.1957"], ["101"], ["1.4115", "0.00055"]], [["303.15"], ["0.298"], ["101"], ["1.41181", "0.00054"]], [["303.15"], ["0.3832"], ["101"], ["1.41165", "0.00053"]], [["303.15"], ["0.4881"], ["101"], ["1.41115", "0.00053"]], [["303.15"], ["0.6047"], ["101"], ["1.4104", "0.00052"]], [["303.15"], ["0.6937"], ["101"], ["1.40976", "0.00052"]], [["303.15"], ["0.8055"], ["101"], ["1.40893", "0.00052"]], [["303.15"], ["0.8532"], ["101"], ["1.40857", "0.00052"]], [["303.15"], ["1"], ["101"], ["1.40746", "0.00052"]], [["308.15"], ["0"], ["101"], ["1.40578", "0.00062"]], [["308.15"], ["0.1127"], ["101"], ["1.40849", "0.00057"]], [["308.15"], ["0.1957"], ["101"], ["1.40962", "0.00055"]], [["308.15"], ["0.298"], ["101"], ["1.41003", "0.00053"]], [["308.15"], ["0.3832"], ["101"], ["1.40994", "0.00052"]], [["308.15"], ["0.4881"], ["101"], ["1.4095", "0.00051"]], [["308.15"], ["0.6047"], ["101"], ["1.4088", "0.0005"]], [["308.15"], ["0.6937"], ["101"], ["1.40818", "0.0005"]], [["308.15"], ["0.8055"], ["101"], ["1.40737", "0.00049"]], [["308.15"], ["0.8532"], ["101"], ["1.407", "0.0005"]], [["308.15"], ["1"], ["101"], ["1.40585", "0.0005"]], [["313.15"], ["0"], ["101"], ["1.40341", "0.00062"]], [["313.15"], ["0.1127"], ["101"], ["1.40654", "0.00056"]], [["313.15"], ["0.1957"], ["101"], ["1.40785", "0.00054"]], [["313.15"], ["0.298"], ["101"], ["1.40838", "0.00052"]], [["313.15"], ["0.3832"], ["101"], ["1.4084", "0.00051"]], [["313.15"], ["0.4881"], ["101"], ["1.40812", "0.0005"]], [["313.15"], ["0.6047"], ["101"], ["1.40751", "0.00048"]], [["313.15"], ["0.6937"], ["101"], ["1.40694", "0.00048"]], [["313.15"], ["0.8055"], ["101"], ["1.40618", "0.00047"]], [["313.15"], ["0.8532"], ["101"], ["1.40581", "0.00047"]], [["313.15"], ["1"], ["101"], ["1.40468", "0.00047"]], [["318.15"], ["0"], ["101"], ["1.40109", "0.00062"]], [["318.15"], ["0.1127"], ["101"], ["1.40465", "0.00056"]], [["318.15"], ["0.1957"], ["101"], ["1.4061", "0.00054"]], [["318.15"], ["0.298"], ["101"], ["1.40677", "0.00052"]], [["318.15"], ["0.3832"], ["101"], ["1.40691", "0.00051"]], [["318.15"], ["0.4881"], ["101"], ["1.40672", "0.00049"]], [["318.15"], ["0.6047"], ["101"], ["1.40624", "0.00048"]], [["318.15"], ["0.6937"], ["101"], ["1.4057", "0.00048"]], [["318.15"], ["0.8055"], ["101"], ["1.405", "0.00047"]], [["318.15"], ["0.8532"], ["101"], ["1.40464", "0.00047"]], [["318.15"], ["1"], ["101"], ["1.40352", "0.00047"]], [["323.15"], ["0"], ["101"], ["1.39876", "0.00062"]], [["323.15"], ["0.1127"], ["101"], ["1.40274", "0.00063"]], [["323.15"], ["0.1957"], ["101"], ["1.40436", "0.00058"]], [["323.15"], ["0.298"], ["101"], ["1.40518", "0.00054"]], [["323.15"], ["0.3832"], ["101"], ["1.40541", "0.00052"]], [["323.15"], ["0.4881"], ["101"], ["1.40536", "0.0005"]], [["323.15"], ["0.6047"], ["101"], ["1.40499", "0.00049"]], [["323.15"], ["0.6937"], ["101"], ["1.40455", "0.00047"]], [["323.15"], ["0.8055"], ["101"], ["1.4039", "0.00047"]], [["323.15"], ["0.8532"], ["101"], ["1.40354", "0.00047"]], [["323.15"], ["1"], ["101"], ["1.40243", "0.00047"]]], "solvent": null, "footer": "", "dhead": [["Temperature, K", null], ["Mole fraction of 1-butyl-3-methylimidazolium hexafluorophosphate", "Liquid"], ["Pressure, kPa", null], ["Refractive index (Na D-line)", "Liquid"]], "components": [{"sample": [["Source:", "commercial source"], ["Initial purification:", "stated by supplier"], ["Initial purity:", "99 mass %"], ["Final purification:", "gas chromatography;Karl Fischer titration"], ["Final purity:", "99.6 mass %;0.01 water mass %(dried in a desiccator;dried by vacuum heating)"]], "name": "2-propoxyethanol", "formula": "C<SUB>5</SUB>H<SUB>12</SUB>O<SUB>2</SUB>", "mw": "104.15", "idout": "AAUBtI"}, {"mw": "284.19", "idout": "ABChJv", "name": "1-butyl-3-methylimidazolium hexafluorophosphate", "formula": "C<SUB>8</SUB>H<SUB>15</SUB>F<SUB>6</SUB>N<SUB>2</SUB>P", "sample": [["Source:", "commercial source"], ["Initial purification:", "stated by supplier"], ["Initial purity:", "99 mass %"], ["Final purification:", "gas chromatography;Karl Fischer titration"], ["Final purity:", "99.5 mass %;0.01 water mass %(dried in a desiccator;dried by vacuum heating)"]]}], "title": "Refraction, surface tension, and speed of sound: Refractive index (Na D-line)"}