{"expmeth": "Standard Abbe refractometry", "data": [[["298.2"], ["0.2232"], ["0.0998"], ["100"], ["1.4155", "0.002"]], [["298.2"], ["0.2314"], ["0.2989"], ["100"], ["1.473", "0.002"]], [["298.2"], ["0.2511"], ["0.2493"], ["100"], ["1.463", "0.002"]], [["298.2"], ["0.264"], ["0.1996"], ["100"], ["1.45", "0.002"]], [["298.2"], ["0.3051"], ["0.1489"], ["100"], ["1.435", "0.002"]], [["298.2"], ["0.3372"], ["0.3054"], ["100"], ["1.4805", "0.002"]], [["298.2"], ["0.3799"], ["0.2503"], ["100"], ["1.4695", "0.002"]], [["298.2"], ["0.3984"], ["0.2018"], ["100"], ["1.4545", "0.002"]], [["298.2"], ["0.425"], ["0.1511"], ["100"], ["1.434", "0.002"]], [["298.2"], ["0.4489"], ["0.1004"], ["100"], ["1.413", "0.002"]], [["298.2"], ["0.466"], ["0.3015"], ["100"], ["1.486", "0.002"]], [["298.2"], ["0.4712"], ["0.1498"], ["100"], ["1.4375", "0.002"]], [["298.2"], ["0.498"], ["0.2468"], ["100"], ["1.4725", "0.002"]], [["298.2"], ["0.5398"], ["0.2002"], ["100"], ["1.4535", "0.002"]], [["298.2"], ["0.6773"], ["0.0999"], ["100"], ["1.4255", "0.002"]], [["308.2"], ["0.2232"], ["0.0998"], ["100"], ["1.4125", "0.002"]], [["308.2"], ["0.2314"], ["0.2989"], ["100"], ["1.462", "0.002"]], [["308.2"], ["0.2511"], ["0.2493"], ["100"], ["1.454", "0.002"]], [["308.2"], ["0.264"], ["0.1996"], ["100"], ["1.4425", "0.002"]], [["308.2"], ["0.3051"], ["0.1489"], ["100"], ["1.43", "0.002"]], [["308.2"], ["0.3372"], ["0.3054"], ["100"], ["1.4745", "0.002"]], [["308.2"], ["0.3799"], ["0.2503"], ["100"], ["1.4635", "0.002"]], [["308.2"], ["0.3984"], ["0.2018"], ["100"], ["1.448", "0.002"]], [["308.2"], ["0.425"], ["0.1511"], ["100"], ["1.4255", "0.002"]], [["308.2"], ["0.4489"], ["0.1004"], ["100"], ["1.408", "0.002"]], [["308.2"], ["0.466"], ["0.3015"], ["100"], ["1.4765", "0.002"]], [["308.2"], ["0.4712"], ["0.1498"], ["100"], ["1.4315", "0.002"]], [["308.2"], ["0.498"], ["0.2468"], ["100"], ["1.4655", "0.002"]], [["308.2"], ["0.5398"], ["0.2002"], ["100"], ["1.447", "0.002"]], [["308.2"], ["0.6773"], ["0.0999"], ["100"], ["1.4195", "0.002"]], [["318.2"], ["0.2232"], ["0.3054"], ["100"], ["1.4675", "0.002"]], [["318.2"], ["0.2314"], ["0.2493"], ["100"], ["1.4505", "0.002"]], [["318.2"], ["0.2511"], ["0.1996"], ["100"], ["1.438", "0.002"]], [["318.2"], ["0.264"], ["0.1498"], ["100"], ["1.4265", "0.002"]], [["318.2"], ["0.3051"], ["0.0998"], ["100"], ["1.405", "0.002"]], [["318.2"], ["0.3372"], ["0.1004"], ["100"], ["1.4025", "0.002"]], [["318.2"], ["0.3799"], ["0.2503"], ["100"], ["1.4565", "0.002"]], [["318.2"], ["0.3984"], ["0.2018"], ["100"], ["1.443", "0.002"]], [["318.2"], ["0.425"], ["0.1511"], ["100"], ["1.4204", "0.002"]], [["318.2"], ["0.4489"], ["0.1004"], ["100"], ["1.4025", "0.002"]], [["318.2"], ["0.466"], ["0.2468"], ["100"], ["1.457", "0.002"]], [["318.2"], ["0.4712"], ["0.0999"], ["100"], ["1.4155", "0.002"]], [["318.2"], ["0.498"], ["0.2002"], ["100"], ["1.44", "0.002"]], [["318.2"], ["0.5398"], ["0.1489"], ["100"], ["1.4235", "0.002"]], [["318.2"], ["0.6773"], ["0.3015"], ["100"], ["1.4695", "0.002"]]], "solvent": null, "footer": "", "dhead": [["Temperature, K", null], ["Mole fraction of water", "Liquid"], ["Mole fraction of 1-ethyl-3-methylimidazolium bromide", "Liquid"], ["Pressure, kPa", null], ["Refractive index (Na D-line)", "Liquid"]], "components": [{"formula": "C<SUB>3</SUB>H<SUB>8</SUB>O", "name": "propan-1-ol", "mw": "60.10", "idout": "AALcLI", "sample": [["Source:", "commercial source"], ["Purification:", "stated by supplier"], ["Purity:", "99.0 mass %"]]}, {"sample": [["Source:", "commercial source"], ["Purification:", "estimated by the compiler"], ["Purity:", "99.8 mol %(fractional distillation)"]], "formula": "H<SUB>2</SUB>O", "name": "water", "idout": "AADYJk", "mw": "18.02"}, {"sample": [["Source:", "commercial source"], ["Purification:", "stated by supplier"], ["Purity:", "98 mass %"]], "name": "1-ethyl-3-methylimidazolium bromide", "formula": "C<SUB>6</SUB>H<SUB>11</SUB>BrN<SUB>2</SUB>", "mw": "191.07", "idout": "AAkmTS"}], "title": "Refraction, surface tension, and speed of sound: Refractive index (Na D-line)", "phases": ["Liquid"], "ref": {"title": "Conductometric and refractometric study of 1-Ethyl-3-methylimidazolium Bromide ionic liquid in water + ethanol/ 1-propanol mixtures at T = (298.2, 308.2 and 318.2) K", "full": "Khoshalhan-Rastekenari, M.; Ghalami-Choobar, B.; Gilani, A. G. (2017) J. Mol. Liq. 237, 402-412."}, "constr": []}