{"phases": ["Liquid"], "constr": [], "ref": {"title": "Insight into the solute-solvent interactions by physicochemical and excess properties in binary systems of the ether- and allyl-based functionalized ionic liquids with acetonitrile", "full": "Fang, D.; Li, L.; Miao, J.; Gao, P.; Zhang, Y.; Hong, M.; Liu, J.; Wei, J. (2022) J. Taiwan Inst. Chem. Eng. 133, 104275."}, "expmeth": "Vibrating tube method", "footer": "", "data": [[["288.15"], ["100"], ["1510.6", "2.1"]], [["293.15"], ["100"], ["1505.4", "2.1"]], [["298.15"], ["100"], ["1500.3", "2"]], [["303.15"], ["100"], ["1495.3", "2"]], [["308.15"], ["100"], ["1490.2", "2"]], [["313.15"], ["100"], ["1485.2", "2"]], [["318.15"], ["100"], ["1480.2", "2"]]], "solvent": null, "dhead": [["Temperature, K", null], ["Pressure, kPa", null], ["Specific density, kg/m<SUP>3</SUP>", "Liquid"]], "title": "Volumetric properties: Specific density", "components": [{"formula": "C<SUB>9</SUB>H<SUB>11</SUB>F<SUB>6</SUB>N<SUB>3</SUB>O<SUB>4</SUB>S<SUB>2</SUB>", "name": "1-allyl-3-methyl-1H-imidazolium bis((trifluoromethyl)sulfonyl)amide", "mw": "403.31", "idout": "ABZdDq", "sample": [["Source:", "synthesized by the authors"], ["Purification:", "estimated by the compiler"], ["Purity:", "98 mass %(dried by vacuum heating)"]]}]}