{"title": "Volumetric properties: Specific density", "components": [{"formula": "C<SUB>13</SUB>H<SUB>22</SUB>ClN", "name": "N-octylpyridinium chloride", "idout": "AArpEf", "mw": "227.78", "sample": [["Source:", "synthesized by the authors"], ["Purification:", "acid-base titration"], ["Purity:", "98 mol %"]]}, {"sample": [["Source:", "commercial source"], ["Purification:", "estimated by the compiler"], ["Purity:", "99.8 mass %"]], "mw": "18.02", "idout": "AADYJk", "name": "water", "formula": "H<SUB>2</SUB>O"}], "dhead": [["Temperature, K", null], ["Mole fraction of water", "Liquid"], ["Pressure, kPa", null], ["Specific density, kg/m<SUP>3</SUP>", "Liquid"]], "footer": "", "data": [[["308.15"], ["0.0625"], ["101"], ["1128.7", "2.2"]], [["308.15"], ["0.1156"], ["101"], ["1128.6", "2.2"]], [["308.15"], ["0.2085"], ["101"], ["1128.3", "2.1"]], [["308.15"], ["0.2545"], ["101"], ["1128.1", "2.1"]], [["308.15"], ["0.306"], ["101"], ["1127.8", "2.1"]], [["308.15"], ["0.4127"], ["101"], ["1126.7", "2"]], [["308.15"], ["0.4534"], ["101"], ["1126.1", "2"]], [["308.15"], ["0.4995"], ["101"], ["1125.2", "2"]], [["308.15"], ["0.6103"], ["101"], ["1121.7", "2"]], [["308.15"], ["0.6508"], ["101"], ["1119.7", "2"]], [["308.15"], ["0.6962"], ["101"], ["1116.7", "2"]], [["308.15"], ["0.7542"], ["101"], ["1111.3", "2"]], [["308.15"], ["0.8086"], ["101"], ["1103.6", "2"]], [["308.15"], ["0.8512"], ["101"], ["1094.8", "2"]], [["308.15"], ["0.9009"], ["101"], ["1078.8", "2"]], [["308.15"], ["0.9485"], ["101"], ["1052.5", "2"]], [["318.15"], ["0.0625"], ["101"], ["1122.8", "2.2"]], [["318.15"], ["0.1156"], ["101"], ["1122.6", "2.2"]], [["318.15"], ["0.2085"], ["101"], ["1122.2", "2.1"]], [["318.15"], ["0.2545"], ["101"], ["1122", "2.1"]], [["318.15"], ["0.306"], ["101"], ["1121.6", "2.1"]], [["318.15"], ["0.4127"], ["101"], ["1120.5", "2"]], [["318.15"], ["0.4534"], ["101"], ["1119.9", "2"]], [["318.15"], ["0.4995"], ["101"], ["1119", "2"]], [["318.15"], ["0.6103"], ["101"], ["1115.2", "2"]], [["318.15"], ["0.6508"], ["101"], ["1113.1", "2"]], [["318.15"], ["0.6962"], ["101"], ["1110", "2"]], [["318.15"], ["0.7542"], ["101"], ["1104.4", "2"]], [["318.15"], ["0.8086"], ["101"], ["1096.6", "2"]], [["318.15"], ["0.8512"], ["101"], ["1087.7", "2"]], [["318.15"], ["0.9009"], ["101"], ["1071.9", "2"]], [["318.15"], ["0.9485"], ["101"], ["1046.4", "2"]]], "solvent": null, "expmeth": "Vibrating tube method", "constr": [], "ref": {"full": "Sastry, N. V.; Ravalji, I. R. (2016) J. Chem. Eng. Data 61(11), 3834-3848.", "title": "Densities, Speeds of Sound, and Excess and Partial Excess Properties of Room Temperature Ionic Liquids of Type [Cnpy][X] or [Cn4mpy][X] (Where n = 6 or 8, [X] = Cl  or Br ) + Water Binary Mixtures at T = (308.15 and 318.15) K"}, "phases": ["Liquid"]}