{"footer": "", "data": [[["0.4382"], ["101"], ["298.15"], ["1535.1", "1.3"]], [["0.5056"], ["101"], ["298.15"], ["1476.2", "1.2"]], [["0.5794"], ["101"], ["298.15"], ["1418.5", "1.1"]], [["0.6654"], ["101"], ["298.15"], ["1358.76", "0.95"]], [["0.7593"], ["101"], ["298.15"], ["1301.41", "0.84"]], [["0.8693"], ["101"], ["298.15"], ["1242.67", "0.76"]], [["0.9422"], ["101"], ["298.15"], ["1208.01", "0.7"]]], "solvent": null, "expmeth": "Vibrating tube method", "title": "Volumetric properties: Specific density", "components": [{"sample": [["Source:", "commercial source"], ["Purification:", "stated by supplier"], ["Purity:", "99 mass %"], ["Purity analysis:", "molecular sieve treatment"]], "formula": "C<SUB>2</SUB>H<SUB>4</SUB>Br<SUB>2</SUB>", "name": "1,2-dibromoethane", "idout": "AAkGpQ", "mw": "187.86"}, {"sample": [["Source:", "commercial source"], ["Initial purification:", "stated by supplier"], ["Initial purity:", "99 mass %"], ["Final purification:", "Karl Fischer titration"], ["Final purity:", "0.0304 water mass %(de-gassed by boiling or ultrasonically)"]], "name": "1-butyl-4-methylpyridinium tetrafluoroborate", "formula": "C<SUB>10</SUB>H<SUB>16</SUB>BF<SUB>4</SUB>N", "mw": "237.05", "idout": "AAtevY"}], "dhead": [["Mole fraction of 1-butyl-4-methylpyridinium tetrafluoroborate", "Liquid"], ["Pressure, kPa", null], ["Temperature, K", null], ["Specific density, kg/m<SUP>3</SUP>", "Liquid"]], "phases": ["Liquid"], "constr": [], "ref": {"title": "COSMO-RS analysis on mixing properties obtained for the systems 1-butyl-X-methylpyridinium tetrafluoroborate [X = 2,3,4] and 1,x-dibromoalkanes [x = 1 6]w", "full": "Navas, A.; Ortega, J.; Palomar, J.; Diaz, C.; Vreekamp, R. (2011) Phys. Chem. Chem. Phys. 13, 7751-7759."}}