{"ref": {"title": "Characterization of the solubilizing ability of short-chained glycol-grafted ammonium and phosphonium ionic liquids", "full": "Mutelet, F.; Hussard, C.; Baker, G. A.; Zhao, H.; Churchill, B.; Acree, Jr., W. E. (2020) J. Mol. Liq. 304, 112786."}, "constr": [], "phases": ["Liquid"], "dhead": [["Temperature, K", null], ["Pressure, kPa", null], ["Specific density, kg/m<SUP>3</SUP>", "Liquid"]], "components": [{"formula": "C<SUB>11</SUB>H<SUB>22</SUB>F<SUB>6</SUB>NO<SUB>5</SUB>PS<SUB>2</SUB>", "name": "triethyl(2-methoxyethyl)phosphonium bis((trifluoromethyl)sulfonyl)amide", "idout": "ABjxLZ", "mw": "457.38", "sample": [["Source:", "synthesized by the authors"], ["Purification:", "estimated by the compiler"], ["Purity:", "98 mass %(dried by vacuum heating;solvent extraction)"]]}], "title": "Volumetric properties: Specific density", "expmeth": "Vibrating tube method", "solvent": null, "data": [[["293.15"], ["101.325"], ["1380.3", "3.2"]], [["298.15"], ["101.325"], ["1375.7", "3.2"]], [["303.15"], ["101.325"], ["1371.2", "3.1"]], [["308.15"], ["101.325"], ["1366.7", "3.1"]], [["313.15"], ["101.325"], ["1362.2", "3.1"]], [["318.15"], ["101.325"], ["1357.7", "3.1"]], [["323.15"], ["101.325"], ["1353.2", "3.1"]], [["328.15"], ["101.325"], ["1348.8", "3.1"]], [["333.15"], ["101.325"], ["1344.3", "3.1"]], [["338.15"], ["101.325"], ["1339.9", "3.1"]], [["343.15"], ["101.325"], ["1335.5", "3"]], [["348.15"], ["101.325"], ["1331", "3"]], [["353.15"], ["101.325"], ["1326.7", "3"]], [["358.15"], ["101.325"], ["1322.3", "3"]], [["363.15"], ["101.325"], ["1318", "3"]], [["368.15"], ["101.325"], ["1313.7", "3"]], [["373.15"], ["101.325"], ["1309.3", "3"]]], "footer": ""}