{"ref": {"title": "Insight into the solute-solvent interactions by physicochemical and excess properties in binary systems of the ether- and allyl-based functionalized ionic liquids with acetonitrile", "full": "Fang, D.; Li, L.; Miao, J.; Gao, P.; Zhang, Y.; Hong, M.; Liu, J.; Wei, J. (2022) J. Taiwan Inst. Chem. Eng. 133, 104275."}, "constr": [], "phases": ["Liquid"], "title": "Volumetric properties: Specific density", "components": [{"sample": [["Source:", "synthesized by the authors"], ["Purification:", "estimated by the compiler"], ["Purity:", "98 mass %(dried by vacuum heating)"]], "idout": "AAoWKo", "mw": "210.28", "name": "N-(2-methoxyethyl)-N-methylpyrrolidinium dicyanamide", "formula": "C<SUB>10</SUB>H<SUB>18</SUB>N<SUB>4</SUB>O"}, {"name": "acetonitrile", "formula": "C<SUB>2</SUB>H<SUB>3</SUB>N", "mw": "41.05", "idout": "AAHueB", "sample": [["Source:", "commercial source"], ["Purification:", "stated by supplier"], ["Purity:", "99.9 mass %"], ["Purity analysis:", "fractional distillation"]]}], "dhead": [["Temperature, K", null], ["Mole fraction of N-(2-methoxyethyl)-N-methylpyrrolidinium dicyanamide", "Liquid"], ["Pressure, kPa", null], ["Specific density, kg/m<SUP>3</SUP>", "Liquid"]], "footer": "", "solvent": null, "data": [[["288.15"], ["0"], ["100"], ["787.527", "0.15"]], [["288.15"], ["0.1001"], ["100"], ["919.2", "1.5"]], [["288.15"], ["0.2"], ["100"], ["1002.3", "0.99"]], [["288.15"], ["0.3"], ["100"], ["1059.45", "0.71"]], [["288.15"], ["0.4"], ["100"], ["1101.49", "0.57"]], [["288.15"], ["0.5002"], ["100"], ["1133.2", "0.54"]], [["288.15"], ["0.6002"], ["100"], ["1158.53", "0.59"]], [["288.15"], ["0.7001"], ["100"], ["1176.97", "0.71"]], [["288.15"], ["0.8"], ["100"], ["1192.91", "0.88"]], [["288.15"], ["0.8999"], ["100"], ["1205.9", "1.1"]], [["288.15"], ["1"], ["100"], ["1215.5", "1.3"]], [["293.15"], ["0"], ["100"], ["782.169", "0.15"]], [["293.15"], ["0.1001"], ["100"], ["914.5", "1.5"]], [["293.15"], ["0.2"], ["100"], ["998.082", "0.99"]], [["293.15"], ["0.3"], ["100"], ["1055.5", "0.72"]], [["293.15"], ["0.4"], ["100"], ["1097.74", "0.57"]], [["293.15"], ["0.5002"], ["100"], ["1129.58", "0.54"]], [["293.15"], ["0.6002"], ["100"], ["1155.01", "0.59"]], [["293.15"], ["0.7001"], ["100"], ["1173.51", "0.7"]], [["293.15"], ["0.8"], ["100"], ["1189.52", "0.87"]], [["293.15"], ["0.8999"], ["100"], ["1202.6", "1.1"]], [["293.15"], ["1"], ["100"], ["1212.2", "1.3"]], [["298.15"], ["0"], ["100"], ["776.766", "0.15"]], [["298.15"], ["0.1001"], ["100"], ["909.9", "1.5"]], [["298.15"], ["0.2"], ["100"], ["993.9", "1"]], [["298.15"], ["0.3"], ["100"], ["1051.55", "0.72"]], [["298.15"], ["0.4"], ["100"], ["1093.98", "0.57"]], [["298.15"], ["0.5002"], ["100"], ["1125.95", "0.54"]], [["298.15"], ["0.6002"], ["100"], ["1151.49", "0.58"]], [["298.15"], ["0.7001"], ["100"], ["1170.05", "0.7"]], [["298.15"], ["0.8"], ["100"], ["1186.13", "0.87"]], [["298.15"], ["0.8999"], ["100"], ["1199.3", "1.1"]], [["298.15"], ["1"], ["100"], ["1209", "1.3"]], [["303.15"], ["0"], ["100"], ["771.333", "0.15"]], [["303.15"], ["0.1001"], ["100"], ["905.2", "1.5"]], [["303.15"], ["0.2"], ["100"], ["989.6", "1"]], [["303.15"], ["0.3"], ["100"], ["1047.61", "0.72"]], [["303.15"], ["0.4"], ["100"], ["1090.24", "0.57"]], [["303.15"], ["0.5002"], ["100"], ["1122.35", "0.54"]], [["303.15"], ["0.6002"], ["100"], ["1147.98", "0.58"]], [["303.15"], ["0.7001"], ["100"], ["1166.61", "0.69"]], [["303.15"], ["0.8"], ["100"], ["1182.75", "0.86"]], [["303.15"], ["0.8999"], ["100"], ["1195.9", "1.1"]], [["303.15"], ["1"], ["100"], ["1205.7", "1.3"]], [["308.15"], ["0"], ["100"], ["765.868", "0.15"]], [["308.15"], ["0.1001"], ["100"], ["900.6", "1.5"]], [["308.15"], ["0.2"], ["100"], ["985.4", "1"]], [["308.15"], ["0.3"], ["100"], ["1043.68", "0.73"]], [["308.15"], ["0.4"], ["100"], ["1086.5", "0.58"]], [["308.15"], ["0.5002"], ["100"], ["1118.75", "0.54"]], [["308.15"], ["0.6002"], ["100"], ["1144.49", "0.58"]], [["308.15"], ["0.7001"], ["100"], ["1163.19", "0.69"]], [["308.15"], ["0.8"], ["100"], ["1179.38", "0.86"]], [["308.15"], ["0.8999"], ["100"], ["1192.6", "1.1"]], [["308.15"], ["1"], ["100"], ["1202.5", "1.3"]], [["313.15"], ["0"], ["100"], ["760.373", "0.15"]], [["313.15"], ["0.1001"], ["100"], ["895.9", "1.6"]], [["313.15"], ["0.2"], ["100"], ["981.2", "1"]], [["313.15"], ["0.3"], ["100"], ["1039.75", "0.73"]], [["313.15"], ["0.4"], ["100"], ["1082.78", "0.58"]], [["313.15"], ["0.5002"], ["100"], ["1115.17", "0.54"]], [["313.15"], ["0.6002"], ["100"], ["1141.02", "0.58"]], [["313.15"], ["0.7001"], ["100"], ["1159.79", "0.69"]], [["313.15"], ["0.8"], ["100"], ["1176.04", "0.85"]], [["313.15"], ["0.8999"], ["100"], ["1189.3", "1"]], [["313.15"], ["1"], ["100"], ["1199.2", "1.3"]], [["318.15"], ["0"], ["100"], ["754.842", "0.15"]], [["318.15"], ["0.1001"], ["100"], ["891.2", "1.6"]], [["318.15"], ["0.2"], ["100"], ["977", "1"]], [["318.15"], ["0.3"], ["100"], ["1035.83", "0.73"]], [["318.15"], ["0.4"], ["100"], ["1079.06", "0.58"]], [["318.15"], ["0.5002"], ["100"], ["1111.61", "0.54"]], [["318.15"], ["0.6002"], ["100"], ["1137.56", "0.57"]], [["318.15"], ["0.7001"], ["100"], ["1156.4", "0.68"]], [["318.15"], ["0.8"], ["100"], ["1172.72", "0.85"]], [["318.15"], ["0.8999"], ["100"], ["1186", "1"]], [["318.15"], ["1"], ["100"], ["1196", "1.3"]]], "expmeth": "Vibrating tube method"}