{"data": [[["298.15"], ["0.045"], ["101"], ["1145.9", "1.4"]], [["298.15"], ["0.091"], ["101"], ["1145.7", "1.3"]], [["298.15"], ["0.126"], ["101"], ["1145.4", "1.3"]], [["298.15"], ["0.152"], ["101"], ["1145.3", "1.3"]], [["298.15"], ["0.193"], ["101"], ["1144.9", "1.2"]], [["298.15"], ["0.267"], ["101"], ["1143.9", "1.2"]], [["298.15"], ["0.335"], ["101"], ["1143", "1.1"]], [["303.15"], ["0.045"], ["101"], ["1143", "1.4"]], [["303.15"], ["0.091"], ["101"], ["1142.7", "1.3"]], [["303.15"], ["0.126"], ["101"], ["1142.4", "1.3"]], [["303.15"], ["0.152"], ["101"], ["1142.3", "1.3"]], [["303.15"], ["0.193"], ["101"], ["1141.8", "1.2"]], [["303.15"], ["0.267"], ["101"], ["1140.9", "1.2"]], [["303.15"], ["0.335"], ["101"], ["1140.1", "1.1"]], [["313.15"], ["0.045"], ["101"], ["1136.9", "1.4"]], [["313.15"], ["0.091"], ["101"], ["1136.7", "1.3"]], [["313.15"], ["0.126"], ["101"], ["1136.6", "1.3"]], [["313.15"], ["0.152"], ["101"], ["1136.4", "1.3"]], [["313.15"], ["0.193"], ["101"], ["1136", "1.2"]], [["313.15"], ["0.267"], ["101"], ["1135.1", "1.2"]], [["313.15"], ["0.335"], ["101"], ["1134.4", "1.1"]], [["323.15"], ["0.045"], ["101"], ["1131", "1.4"]], [["323.15"], ["0.091"], ["101"], ["1131", "1.3"]], [["323.15"], ["0.126"], ["101"], ["1130.7", "1.3"]], [["323.15"], ["0.152"], ["101"], ["1130.6", "1.3"]], [["323.15"], ["0.193"], ["101"], ["1130.2", "1.2"]], [["323.15"], ["0.267"], ["101"], ["1129.5", "1.2"]], [["323.15"], ["0.335"], ["101"], ["1128.6", "1.1"]], [["328.15"], ["0.045"], ["101"], ["1128.2", "1.4"]], [["328.15"], ["0.091"], ["101"], ["1128.1", "1.3"]], [["328.15"], ["0.126"], ["101"], ["1128.1", "1.3"]], [["328.15"], ["0.152"], ["101"], ["1127.9", "1.3"]], [["328.15"], ["0.193"], ["101"], ["1127.5", "1.2"]], [["328.15"], ["0.267"], ["101"], ["1126.7", "1.2"]], [["328.15"], ["0.335"], ["101"], ["1125.8", "1.1"]], [["333.15"], ["0.045"], ["101"], ["1125.4", "1.4"]], [["333.15"], ["0.091"], ["101"], ["1125.4", "1.3"]], [["333.15"], ["0.126"], ["101"], ["1125.2", "1.3"]], [["333.15"], ["0.152"], ["101"], ["1125", "1.3"]], [["333.15"], ["0.193"], ["101"], ["1124.7", "1.2"]], [["333.15"], ["0.267"], ["101"], ["1124", "1.2"]], [["333.15"], ["0.335"], ["101"], ["1123", "1.1"]], [["343.15"], ["0.045"], ["101"], ["1119.9", "1.4"]], [["343.15"], ["0.091"], ["101"], ["1119.8", "1.3"]], [["343.15"], ["0.126"], ["101"], ["1119.7", "1.3"]], [["343.15"], ["0.152"], ["101"], ["1119.5", "1.3"]], [["343.15"], ["0.193"], ["101"], ["1119.1", "1.2"]], [["343.15"], ["0.267"], ["101"], ["1118.3", "1.2"]], [["343.15"], ["0.335"], ["101"], ["1117.4", "1.1"]], [["353.15"], ["0.045"], ["101"], ["1114.4", "1.4"]], [["353.15"], ["0.091"], ["101"], ["1114.3", "1.3"]], [["353.15"], ["0.126"], ["101"], ["1114.2", "1.3"]], [["353.15"], ["0.152"], ["101"], ["1113.9", "1.3"]], [["353.15"], ["0.193"], ["101"], ["1113.6", "1.2"]], [["353.15"], ["0.267"], ["101"], ["1112.8", "1.2"]], [["353.15"], ["0.335"], ["101"], ["1111.8", "1.1"]], [["363.15"], ["0.045"], ["101"], ["1108.8", "1.3"]], [["363.15"], ["0.091"], ["101"], ["1108.9", "1.3"]], [["363.15"], ["0.126"], ["101"], ["1108.7", "1.3"]], [["363.15"], ["0.152"], ["101"], ["1108.4", "1.2"]], [["363.15"], ["0.193"], ["101"], ["1108", "1.2"]], [["363.15"], ["0.267"], ["101"], ["1107.3", "1.2"]], [["363.15"], ["0.335"], ["101"], ["1106.3", "1.1"]], [["373.15"], ["0.045"], ["101"], ["1103.6", "1.3"]], [["373.15"], ["0.091"], ["101"], ["1103.5", "1.3"]], [["373.15"], ["0.126"], ["101"], ["1103.3", "1.3"]], [["373.15"], ["0.152"], ["101"], ["1103", "1.2"]], [["373.15"], ["0.193"], ["101"], ["1102.7", "1.2"]], [["373.15"], ["0.267"], ["101"], ["1101.8", "1.2"]], [["373.15"], ["0.335"], ["101"], ["1100.9", "1.1"]]], "solvent": null, "footer": "", "expmeth": "Vibrating tube method", "components": [{"name": "water", "formula": "H<SUB>2</SUB>O", "idout": "AADYJk", "mw": "18.02", "sample": [["Source:", "commercial source"], ["Purification:", "stated by supplier"], ["Purity:", "99.8 mass %"]]}, {"sample": [["Source:", "commercial source"], ["Purification:", "stated by supplier"], ["Purity:", "98 mass %"], ["Purity analysis:", "dried by vacuum heating"]], "mw": "158.63", "idout": "AAeaVk", "formula": "C<SUB>7</SUB>H<SUB>11</SUB>ClN<SUB>2</SUB>", "name": "1-allyl-3-methylimidazolium chloride"}], "title": "Volumetric properties: Specific density", "dhead": [["Temperature, K", null], ["Mole fraction of water", "Liquid"], ["Pressure, kPa", null], ["Specific density, kg/m<SUP>3</SUP>", "Liquid"]], "phases": ["Liquid"], "constr": [], "ref": {"full": "Jimenez de la Parra, C.; Zambrano, J. R.; Bermejo, M. D.; Martin, A.; Segovia, J. J.; Cocero, M. J. (2015) J. Chem. Thermodyn. 91, 8-16.", "title": "Influence of water concentration in the viscosities and densities of cellulose dissolving ionic liquids. Correlation of viscosity data"}}