{"solvent": null, "data": [[["375", "1.1"]]], "footer": "", "expmeth": "DSC/DTA", "components": [{"sample": [["Source:", "commercial source"], ["Initial purification:", "stated by supplier"], ["Initial purity:", "99 mass %"], ["Final purification:", "Karl Fischer titration"], ["Final purity:", "0.000073 water mass %"]], "formula": "C<SUB>20</SUB>H<SUB>44</SUB>BrN", "name": "tetrapentylammonium bromide", "mw": "378.48", "idout": "ABUomC"}], "title": "Phase transition properties: Normal melting temperature", "dhead": [["Normal melting temperature, K"]], "phases": ["Crystal", "Liquid"], "ref": {"title": "Activity modelling of the solid-liquid equilibrium of deep eutectic solvents", "full": "Kollau, L. J.B.M.; Vis, M.; van den Bruinhorst, A.; de With, G.; Tuinier, R. (2019) Pure Appl. Chem. 91(8), 1341-1349."}, "constr": ["Pressure of 1 atm"]}