{"phases": ["Liquid"], "constr": [], "ref": {"title": "Characterization of Aqueous 1-Ethyl-3-Methylimidazolium Ionic Liquids for Calculation of Ion Dissociation", "full": "Nordness, O.; Simoni, L. D.; Stadtherr, M. A.; Brennecke, J. F. (2019) J. Phys. Chem. B 123(6), 1348-1358."}, "footer": "", "data": [[["293.15"], ["0"], ["101"], ["1387", "28"]], [["293.15"], ["0.27"], ["101"], ["1373", "28"]], [["293.15"], ["0.488"], ["101"], ["1352", "28"]], [["293.15"], ["0.537"], ["101"], ["1347", "28"]], [["293.15"], ["0.609"], ["101"], ["1333", "28"]], [["293.15"], ["0.784"], ["101"], ["1285", "28"]], [["293.15"], ["0.863"], ["101"], ["1242", "28"]], [["293.15"], ["0.906"], ["101"], ["1201", "28"]], [["293.15"], ["0.936"], ["101"], ["1161", "28"]], [["293.15"], ["0.959"], ["101"], ["1126", "28"]], [["293.15"], ["0.971"], ["101"], ["1091", "28"]], [["293.15"], ["0.983"], ["101"], ["1058", "28"]], [["293.15"], ["0.988"], ["101"], ["1043", "28"]], [["293.15"], ["0.992"], ["101"], ["1027", "28"]], [["293.15"], ["0.995"], ["101"], ["1019", "28"]], [["293.15"], ["0.996"], ["101"], ["1012", "28"]], [["293.15"], ["0.998"], ["101"], ["1007", "28"]], [["293.15"], ["0.999"], ["101"], ["1001", "28"]], [["298.15"], ["0"], ["101"], ["1383", "28"]], [["298.15"], ["0.27"], ["101"], ["1368", "28"]], [["298.15"], ["0.488"], ["101"], ["1348", "28"]], [["298.15"], ["0.537"], ["101"], ["1342", "28"]], [["298.15"], ["0.609"], ["101"], ["1329", "28"]], [["298.15"], ["0.784"], ["101"], ["1281", "28"]], [["298.15"], ["0.863"], ["101"], ["1238", "28"]], [["298.15"], ["0.906"], ["101"], ["1197", "28"]], [["298.15"], ["0.936"], ["101"], ["1158", "28"]], [["298.15"], ["0.959"], ["101"], ["1123", "28"]], [["298.15"], ["0.971"], ["101"], ["1089", "28"]], [["298.15"], ["0.983"], ["101"], ["1056", "28"]], [["298.15"], ["0.988"], ["101"], ["1041", "28"]], [["298.15"], ["0.992"], ["101"], ["1026", "28"]], [["298.15"], ["0.995"], ["101"], ["1018", "28"]], [["298.15"], ["0.996"], ["101"], ["1011", "28"]], [["298.15"], ["0.998"], ["101"], ["1005", "28"]], [["298.15"], ["0.999"], ["101"], ["998", "28"]], [["303.15"], ["0"], ["101"], ["1379", "28"]], [["303.15"], ["0.27"], ["101"], ["1364", "28"]], [["303.15"], ["0.488"], ["101"], ["1344", "28"]], [["303.15"], ["0.537"], ["101"], ["1338", "28"]], [["303.15"], ["0.609"], ["101"], ["1325", "28"]], [["303.15"], ["0.784"], ["101"], ["1277", "28"]], [["303.15"], ["0.863"], ["101"], ["1234", "28"]], [["303.15"], ["0.906"], ["101"], ["1194", "28"]], [["303.15"], ["0.936"], ["101"], ["1155", "28"]], [["303.15"], ["0.959"], ["101"], ["1120", "28"]], [["303.15"], ["0.971"], ["101"], ["1086", "28"]], [["303.15"], ["0.983"], ["101"], ["1054", "28"]], [["303.15"], ["0.988"], ["101"], ["1039", "28"]], [["303.15"], ["0.992"], ["101"], ["1024", "28"]], [["303.15"], ["0.995"], ["101"], ["1016", "28"]], [["303.15"], ["0.996"], ["101"], ["1009", "28"]], [["303.15"], ["0.998"], ["101"], ["1004", "28"]], [["303.15"], ["0.999"], ["101"], ["997", "28"]], [["313.15"], ["0"], ["101"], ["1370", "28"]], [["313.15"], ["0.27"], ["101"], ["1356", "28"]], [["313.15"], ["0.488"], ["101"], ["1336", "28"]], [["313.15"], ["0.537"], ["101"], ["1330", "28"]], [["313.15"], ["0.609"], ["101"], ["1316", "28"]], [["313.15"], ["0.784"], ["101"], ["1269", "28"]], [["313.15"], ["0.863"], ["101"], ["1226", "28"]], [["313.15"], ["0.906"], ["101"], ["1186", "28"]], [["313.15"], ["0.936"], ["101"], ["1148", "28"]], [["313.15"], ["0.959"], ["101"], ["1113", "28"]], [["313.15"], ["0.971"], ["101"], ["1081", "28"]], [["313.15"], ["0.983"], ["101"], ["1050", "28"]], [["313.15"], ["0.988"], ["101"], ["1035", "28"]], [["313.15"], ["0.992"], ["101"], ["1020", "28"]], [["313.15"], ["0.995"], ["101"], ["1012", "28"]], [["313.15"], ["0.996"], ["101"], ["1006", "28"]], [["313.15"], ["0.998"], ["101"], ["1000", "28"]], [["313.15"], ["0.999"], ["101"], ["993", "28"]]], "solvent": null, "expmeth": "Vibrating tube method", "title": "Volumetric properties: Specific density", "components": [{"sample": [["Source:", "commercial source"], ["Purification:", "stated by supplier"], ["Purity:", "99 mass %"]], "mw": "260.23", "idout": "AAyCVz", "formula": "C<SUB>7</SUB>H<SUB>11</SUB>F<SUB>3</SUB>N<SUB>2</SUB>O<SUB>3</SUB>S", "name": "1-ethyl-3-methylimidazolium trifluoromethanesulfonate"}, {"sample": [["Source:", "commercial source"], ["Purification:", "estimated by the compiler"], ["Purity:", "99.5 mass %"]], "formula": "H<SUB>2</SUB>O", "name": "water", "mw": "18.02", "idout": "AADYJk"}], "dhead": [["Temperature, K", null], ["Mole fraction of water", "Liquid"], ["Pressure, kPa", null], ["Specific density, kg/m<SUP>3</SUP>", "Liquid"]]}