{"constr": [], "ref": {"full": "Weiss, H.; Mars, J.; Li, H.; Kircher, G.; Ivanova, O.; Feoktystov, A.; Soltwedel, O.; Bier, M.; Mezger, M. (2017) J. Phys. Chem. B 121(3), 620-629.", "title": "Mesoscopic Correlation Functions in Heterogeneous Ionic Liquids"}, "phases": ["Liquid"], "title": "Volumetric properties: Specific density", "components": [{"mw": "915.78", "idout": "ADUFqy", "formula": "C<SUB>30</SUB>H<SUB>43</SUB>F<SUB>18</SUB>N<SUB>3</SUB>O<SUB>4</SUB>S<SUB>2</SUB>", "name": "1-methyl-3-octadecylimidazolium bis(nonafluorobutanesulfonyl)imide", "sample": [["Source:", "synthesized by the authors"], ["Purification:", "estimated by the compiler"], ["Purity:", "99 mass %(crystallization from melt;crystallization from solution;dried by vacuum heating)"]]}], "dhead": [["Temperature, K", null], ["Pressure, kPa", null], ["Specific density, kg/m<SUP>3</SUP>", "Liquid"]], "footer": "", "data": [[["335.1"], ["101.325"], ["1314", "5"]], [["338.1"], ["101.325"], ["1312", "5"]], [["343"], ["101.325"], ["1308", "5"]], [["348.1"], ["101.325"], ["1303", "5"]], [["353"], ["101.325"], ["1299", "5"]], [["358.1"], ["101.325"], ["1295", "5"]], [["363"], ["101.325"], ["1291", "5"]], [["368.1"], ["101.325"], ["1287", "5"]], [["373"], ["101.325"], ["1283", "5"]], [["378.15"], ["101.325"], ["1279", "5"]], [["383.1"], ["101.325"], ["1275", "5"]], [["388.15"], ["101.325"], ["1271", "5"]], [["393.1"], ["101.325"], ["1267", "5"]], [["398.15"], ["101.325"], ["1263", "5"]]], "solvent": null, "expmeth": "Pycnometric method"}