{"phases": ["Liquid"], "constr": [], "ref": {"full": "Makino, T.; Kanakubo, M.; Masuda, Y.; Umecky, T.; Suzuki, A. (2014) Fluid Phase Equilib. 362, 300.", "title": "CO2 Absorption Properties, Densities, Viscosities, and Electrical Conductivities of Ethylimidazolium and 1-Ethyl-3-Methylimidazolium Ionic Liquids"}, "data": [[["298.15"], ["622.1"], ["0.156"], ["0.0002229", "3.1e-06"]], [["298.15"], ["973.2"], ["0.227"], ["0.000207", "2.9e-06"]], [["298.15"], ["1501.9"], ["0.316"], ["0.0001876", "2.6e-06"]], [["298.15"], ["2270.4"], ["0.418"], ["0.0001653", "2.3e-06"]], [["298.15"], ["2781.6"], ["0.472"], ["0.0001535", "2.2e-06"]], [["298.15"], ["3321"], ["0.523"], ["0.0001427", "2e-06"]], [["298.15"], ["4042.6"], ["0.577"], ["0.0001311", "1.8e-06"]], [["298.15"], ["4610.4"], ["0.615"], ["0.0001231", "1.7e-06"]], [["298.15"], ["4874"], ["0.63"], ["0.0001201", "1.7e-06"]], [["313.15"], ["671.8"], ["0.13"], ["0.0002308", "3.2e-06"]], [["313.15"], ["1053.2"], ["0.192"], ["0.0002169", "3e-06"]], [["313.15"], ["1630.4"], ["0.27"], ["0.0001996", "2.8e-06"]], [["313.15"], ["2447.1"], ["0.364"], ["0.0001791", "2.5e-06"]], [["313.15"], ["3046.3"], ["0.414"], ["0.000168", "2.4e-06"]], [["313.15"], ["3653.1"], ["0.463"], ["0.0001575", "2.2e-06"]], [["313.15"], ["4479.5"], ["0.515"], ["0.0001462", "2e-06"]], [["313.15"], ["5146.4"], ["0.553"], ["0.0001381", "1.9e-06"]], [["313.15"], ["5463.8"], ["0.567"], ["0.0001352", "1.9e-06"]], [["333.15"], ["732.5"], ["0.107"], ["0.0002393", "3.4e-06"]], [["333.15"], ["1151"], ["0.159"], ["0.0002275", "3.2e-06"]], [["333.15"], ["1788.9"], ["0.225"], ["0.0002127", "3e-06"]], [["333.15"], ["2733.1"], ["0.308"], ["0.0001943", "2.7e-06"]], [["333.15"], ["3374"], ["0.355"], ["0.0001837", "2.6e-06"]], [["333.15"], ["4068.3"], ["0.399"], ["0.0001741", "2.4e-06"]], [["333.15"], ["5028.6"], ["0.45"], ["0.000163", "2.3e-06"]], [["333.15"], ["5823.1"], ["0.489"], ["0.0001545", "2.2e-06"]], [["333.15"], ["6532.8"], ["0.514"], ["0.0001494", "2.1e-06"]]], "solvent": null, "footer": "", "expmeth": "Other PVT measurement", "components": [{"formula": "CO<SUB>2</SUB>", "name": "carbon dioxide", "idout": "AAIYzl", "mw": "44.01", "sample": [["Source:", "commercial source"], ["Purification:", "stated by supplier"], ["Purity:", "99.99 mol %"]]}, {"sample": [["Source:", "synthesized by the authors"], ["Purification:", "Karl Fischer titration;NMR (proton)"], ["Purity:", "0.003 water mass %;99 mol %(dried by vacuum heating)"]], "mw": "391.30", "idout": "ABXNZH", "name": "1-ethyl-3-methylimidazolium bis((trifluoromethyl)sulfonyl)imide", "formula": "C<SUB>8</SUB>H<SUB>11</SUB>F<SUB>6</SUB>N<SUB>3</SUB>O<SUB>4</SUB>S<SUB>2</SUB>"}], "title": "Volumetric properties: Molar volume", "dhead": [["Temperature, K", null], ["Pressure, kPa", null], ["Mole fraction of carbon dioxide", "Liquid"], ["Molar volume, m<SUP>3</SUP>/mol", "Liquid"]]}