{"components": [{"sample": [["Source:", "commercial source"], ["Purification:", "stated by supplier"], ["Purity:", "99.9 mass %"]], "mw": "73.09", "idout": "AAOCWD", "name": "dimethylformamide", "formula": "C<SUB>3</SUB>H<SUB>7</SUB>NO"}, {"sample": [["Source:", "commercial source"], ["Purification:", "NMR (proton)"], ["Purity:", "96 mass %"]], "formula": "C<SUB>32</SUB>H<SUB>68</SUB>BrP", "name": "tetradecyltrihexylphosphonium bromide", "mw": "563.77", "idout": "ACEVSf"}], "title": "Volumetric properties: Specific density", "dhead": [["Temperature, K", null], ["Mole fraction of tetradecyltrihexylphosphonium bromide", "Liquid"], ["Pressure, kPa", null], ["Specific density, kg/m<SUP>3</SUP>", "Liquid"]], "data": [[["293.15"], ["0.0374"], ["101"], ["952.28", "0.12"]], [["293.15"], ["0.0791"], ["101"], ["955.06", "0.13"]], [["293.15"], ["0.0932"], ["101"], ["955.76", "0.13"]], [["293.15"], ["0.153"], ["101"], ["957.9", "0.16"]], [["293.15"], ["0.2252"], ["101"], ["959.05", "0.23"]], [["293.15"], ["0.3292"], ["101"], ["959.99", "0.4"]], [["293.15"], ["0.475"], ["101"], ["960.61", "0.76"]], [["293.15"], ["0.5659"], ["101"], ["960.9", "1"]], [["293.15"], ["0.7337"], ["101"], ["961.1", "1.7"]], [["293.15"], ["0.8695"], ["101"], ["961.2", "2.4"]], [["298.15"], ["0.0374"], ["101"], ["947.88", "0.12"]], [["298.15"], ["0.0791"], ["101"], ["950.94", "0.13"]], [["298.15"], ["0.0932"], ["101"], ["951.71", "0.13"]], [["298.15"], ["0.153"], ["101"], ["954.07", "0.16"]], [["298.15"], ["0.2252"], ["101"], ["955.4", "0.23"]], [["298.15"], ["0.3292"], ["101"], ["956.51", "0.4"]], [["298.15"], ["0.475"], ["101"], ["957.26", "0.75"]], [["298.15"], ["0.5659"], ["101"], ["957.6", "1"]], [["298.15"], ["0.7337"], ["101"], ["958", "1.7"]], [["298.15"], ["0.8695"], ["101"], ["958.1", "2.4"]], [["303.15"], ["0.0374"], ["101"], ["943.47", "0.12"]], [["303.15"], ["0.0791"], ["101"], ["946.81", "0.13"]], [["303.15"], ["0.0932"], ["101"], ["947.64", "0.13"]], [["303.15"], ["0.153"], ["101"], ["950.23", "0.16"]], [["303.15"], ["0.2252"], ["101"], ["951.74", "0.23"]], [["303.15"], ["0.3292"], ["101"], ["953.03", "0.4"]], [["303.15"], ["0.475"], ["101"], ["953.9", "0.75"]], [["303.15"], ["0.5659"], ["101"], ["954.3", "1"]], [["303.15"], ["0.7337"], ["101"], ["954.7", "1.7"]], [["303.15"], ["0.8695"], ["101"], ["954.9", "2.4"]], [["308.15"], ["0.0374"], ["101"], ["939.06", "0.12"]], [["308.15"], ["0.0791"], ["101"], ["942.7", "0.13"]], [["308.15"], ["0.0932"], ["101"], ["943.59", "0.14"]], [["308.15"], ["0.153"], ["101"], ["946.4", "0.16"]], [["308.15"], ["0.2252"], ["101"], ["948.11", "0.23"]], [["308.15"], ["0.3292"], ["101"], ["949.55", "0.4"]], [["308.15"], ["0.475"], ["101"], ["950.57", "0.74"]], [["308.15"], ["0.5659"], ["101"], ["951", "1"]], [["308.15"], ["0.7337"], ["101"], ["951.5", "1.7"]], [["308.15"], ["0.8695"], ["101"], ["951.8", "2.4"]], [["313.15"], ["0.0374"], ["101"], ["934.62", "0.13"]], [["313.15"], ["0.0791"], ["101"], ["938.56", "0.13"]], [["313.15"], ["0.0932"], ["101"], ["939.52", "0.14"]], [["313.15"], ["0.153"], ["101"], ["942.56", "0.17"]], [["313.15"], ["0.2252"], ["101"], ["944.46", "0.23"]], [["313.15"], ["0.3292"], ["101"], ["946.05", "0.4"]], [["313.15"], ["0.475"], ["101"], ["947.21", "0.74"]], [["313.15"], ["0.5659"], ["101"], ["947.7", "1"]], [["313.15"], ["0.7337"], ["101"], ["948.3", "1.7"]], [["313.15"], ["0.8695"], ["101"], ["948.6", "2.3"]]], "solvent": null, "footer": "", "expmeth": "Vibrating tube method", "ref": {"title": "Volumetric Properties of the Binary System Trihexyltetradecylphosphonium Bromide (CYPHOS IL 102) + N,N-Dimethylformamide (DMF) at Temperatures from T = 293.15 to 313.15 K at Atmospheric Pressure", "full": "Juarez-Camacho, E. P.; Manriquez-Ramirez, M. E.; Reza-San German, C. M.; Zuniga-Moreno, A. (2012) J. Solution Chem. 41, 1575-1586."}, "constr": [], "phases": ["Liquid"]}