{"phases": ["Liquid"], "constr": [], "ref": {"full": "Zhang, W.; Yi, X.; Yi, Q.; Sun, L. (2022) J. Mol. Liq. 364, 119913.", "title": "Performance evaluation and molecular dynamics simulation in the Liquid-liquid extraction process of low transition temperature mixture + n-hexane + 1,2-Dichloroethane"}, "expmeth": "not reported", "footer": "", "data": [[["298.15"], ["101.3"], ["2"], ["1117.2", "1.3"]], [["308.15"], ["101.3"], ["2"], ["1108", "1.3"]], [["318.15"], ["101.3"], ["2"], ["1099.1", "1.3"]], [["328.15"], ["101.3"], ["2"], ["1090.1", "1.2"]], [["338.15"], ["101.3"], ["2"], ["1081.5", "1.2"]]], "solvent": "tetraethylammonium chloride", "dhead": [["Temperature, K", null], ["Pressure, kPa", null], ["Mole ratio to solvent: 2-oxopropanoic acid", "Liquid"], ["Specific density, kg/m<SUP>3</SUP>", "Liquid"]], "title": "Volumetric properties: Specific density", "components": [{"mw": "165.71", "idout": "AAftPF", "formula": "C<SUB>8</SUB>H<SUB>20</SUB>ClN", "name": "tetraethylammonium chloride", "sample": [["Source:", "commercial source"], ["Purification:", "stated by supplier"], ["Purity:", "98 mass %"]]}, {"sample": [["Source:", "commercial source"], ["Purification:", "stated by supplier"], ["Purity:", "98 mass %"]], "mw": "88.06", "idout": "AAQwdv", "formula": "C<SUB>3</SUB>H<SUB>4</SUB>O<SUB>3</SUB>", "name": "2-oxopropanoic acid"}]}