{"expmeth": "Pycnometric method", "solvent": null, "data": [[["298"], ["101.325"], ["1057.8", "0.8"]], [["303"], ["101.325"], ["1053.8", "0.8"]], [["308"], ["101.325"], ["1051.9", "0.7"]], [["313"], ["101.325"], ["1049.9", "0.8"]], [["318"], ["101.325"], ["1046.6", "0.8"]], [["323"], ["101.325"], ["1044.8", "0.8"]], [["328"], ["101.325"], ["1042", "0.8"]]], "footer": "", "dhead": [["Temperature, K", null], ["Pressure, kPa", null], ["Specific density, kg/m<SUP>3</SUP>", "Liquid"]], "components": [{"name": "1-butyl-3-methylimidazolium acetate", "formula": "C<SUB>10</SUB>H<SUB>18</SUB>N<SUB>2</SUB>O<SUB>2</SUB>", "idout": "AAmGQS", "mw": "198.27", "sample": [["Source:", "commercial source"], ["Purification:", "estimated by the compiler"], ["Purity:", "99 mass %"]]}], "title": "Volumetric properties: Specific density", "phases": ["Liquid"], "constr": [], "ref": {"title": "Physicochemical properties of 1-butyl-3-methylimidazolium acetate", "full": "Bogolitsyn, K. G.; Skrebets, T. E.; Makhova, T. A. (2009) Russ. J. Gen. Chem. 79(1), 125-128."}}