{"dhead": [["Temperature, K", null], ["Pressure, kPa", null], ["Refractive index (Na D-line)", "Liquid"]], "components": [{"sample": [["Source:", "commercial source"], ["Purification:", "stated by supplier"], ["Purity:", "99 mass %"], ["Purity analysis:", "dried by vacuum heating"]], "name": "1-hexyl-1-methylpyrrolidinium bis(trifluoromethanesulfonyl)imide", "formula": "C<SUB>13</SUB>H<SUB>24</SUB>F<SUB>6</SUB>N<SUB>2</SUB>O<SUB>4</SUB>S<SUB>2</SUB>", "mw": "450.46", "idout": "ABigFi"}], "title": "Refraction, surface tension, and speed of sound: Refractive index (Na D-line)", "expmeth": "Standard Abbe refractometry", "data": [[["293.15"], ["101.325"], ["1.4267", "0.0004"]], [["298.15"], ["101.325"], ["1.4258", "0.0004"]], [["303.15"], ["101.325"], ["1.4243", "0.0004"]], [["308.15"], ["101.325"], ["1.423", "0.0004"]], [["313.15"], ["101.325"], ["1.4216", "0.0004"]]], "solvent": null, "footer": "", "constr": [], "ref": {"full": "Warmiska, D.; Cichowska-Kopczyska, I. (2020) J. Mol. Liq. 304, 112754.", "title": "Thermodynamic study of binary mixtures of toluene with ionic liquids, 1-butyl-1-methylpyrrolidinium bis(trifluoromethylsulfonyl)imide, 1-hexyl-1-methylpyrrolidinium bis(trifluoromethylsulfonyl)imide and 1-butylpyridinium bis(trifluoromethylsulfonyl)imide"}, "phases": ["Liquid"]}